gradio-app/app.py
grew_tse-0.1.3.dist-info/licenses/LICENSE
grewtse/__init__.py
grewtse/pipeline.py
grewtse/evaluators/__init__.py
grewtse/evaluators/evaluator.py
grewtse/evaluators/metrics.py
grewtse/preprocessing/__init__.py
grewtse/preprocessing/conllu_parser.py
grewtse/preprocessing/grew_dependencies.py
grewtse/preprocessing/reconstruction.py
grewtse/utils/__init__.py
grewtse/utils/validation.py
grewtse/visualise/__init__.py
grewtse/visualise/visualiser.py
grew_tse-0.1.3.dist-info/METADATA
grew_tse-0.1.3.dist-info/WHEEL
grew_tse-0.1.3.dist-info/top_level.txt
grew_tse-0.1.3.dist-info/RECORD
