Metadata-Version: 2.4
Name: grew-tse
Version: 0.1.3
Summary: A library for the generation of minimal-pair syntactic tests from treebanks for Targeted Syntactic Evaluation of LLMs.
Author-email: Daniel Gallagher <daniel.gallagher.js@gmail.com>
License: MIT
Project-URL: Homepage, https://grew-tse.readthedocs.io/
Project-URL: Issues, https://github.com/DanielGall500/Grew-TSE/issues
Keywords: Targeted Syntactic Evaluation,TSE,LLM,linguistics,dependency-parsing,treebank,syntax
Classifier: Programming Language :: Python :: 3
Classifier: License :: OSI Approved :: MIT License
Classifier: Operating System :: OS Independent
Requires-Python: >=3.8
License-File: LICENSE
Requires-Dist: conllu>=6.0.0
Requires-Dist: grewpy>=0.6.0
Requires-Dist: numpy>=1.24.0
Requires-Dist: pandas>=2.0.0
Provides-Extra: dev
Requires-Dist: pytest>=7.0; extra == "dev"
Requires-Dist: black>=24.0; extra == "dev"
Provides-Extra: eval
Requires-Dist: tokenizers>=0.21.0; extra == "eval"
Requires-Dist: torch>=2.0.0; extra == "eval"
Requires-Dist: transformers>=4.50.0; extra == "eval"
Requires-Dist: plotnine>=0.12.0; extra == "eval"
Dynamic: license-file
